[
    {
        "logo":"https://i.ibb.co/JCjK4Kt/apple.png",
        "title":"Apple",
        "followers":"12,943,179"
    },
    {
        "logo":"https://i.ibb.co/pJStMph/nike.png",
        "title":"Nike",
        "followers":"4,131,428"
    },
    {
        "logo":"https://i.ibb.co/NCgR66R/rog.png",
        "title":"Asus ROG",
        "followers":"343,069"
    },
    {
        "logo":"https://i.ibb.co/8XBNWK1/strive.png",
        "title":"Strive School",
        "followers":"Uncountable"
    },
    {
        "logo":"https://i.ibb.co/xLnkGzm/ua.png",
        "title":"Under Armour",
        "followers":"622,940"
    }
]